{"nodes": [{"id": "d_php_ws_lequocanh_administrator_elements_lqa_mod_thuoctinhhhcls_php", "label": "thuoctinhhhCls.php", "file_type": "code", "source_file": "D:\\PHP_WS\\lequocanh\\administrator\\elements_LQA\\mod\\thuoctinhhhCls.php", "source_location": "L1"}, {"id": "mod_thuoctinhhhcls_thuoctinhhh", "label": "ThuocTinhHH", "file_type": "code", "source_file": "D:\\PHP_WS\\lequocanh\\administrator\\elements_LQA\\mod\\thuoctinhhhCls.php", "source_location": "L4"}, {"id": "mod_thuoctinhhhcls_thuoctinhhh_construct", "label": ".__construct()", "file_type": "code", "source_file": "D:\\PHP_WS\\lequocanh\\administrator\\elements_LQA\\mod\\thuoctinhhhCls.php", "source_location": "L8"}, {"id": "mod_thuoctinhhhcls_thuoctinhhh_thuoctinhhhgetall", "label": ".thuoctinhhhGetAll()", "file_type": "code", "source_file": "D:\\PHP_WS\\lequocanh\\administrator\\elements_LQA\\mod\\thuoctinhhhCls.php", "source_location": "L13"}, {"id": "mod_thuoctinhhhcls_thuoctinhhh_thuoctinhhhadd", "label": ".thuoctinhhhAdd()", "file_type": "code", "source_file": "D:\\PHP_WS\\lequocanh\\administrator\\elements_LQA\\mod\\thuoctinhhhCls.php", "source_location": "L27"}, {"id": "mod_thuoctinhhhcls_thuoctinhhh_thuoctinhhhdelete", "label": ".thuoctinhhhDelete()", "file_type": "code", "source_file": "D:\\PHP_WS\\lequocanh\\administrator\\elements_LQA\\mod\\thuoctinhhhCls.php", "source_location": "L42"}, {"id": "mod_thuoctinhhhcls_thuoctinhhh_thuoctinhhhupdate", "label": ".thuoctinhhhUpdate()", "file_type": "code", "source_file": "D:\\PHP_WS\\lequocanh\\administrator\\elements_LQA\\mod\\thuoctinhhhCls.php", "source_location": "L57"}, {"id": "mod_thuoctinhhhcls_thuoctinhhh_thuoctinhhhgetbyid", "label": ".thuoctinhhhGetbyId()", "file_type": "code", "source_file": "D:\\PHP_WS\\lequocanh\\administrator\\elements_LQA\\mod\\thuoctinhhhCls.php", "source_location": "L98"}, {"id": "mod_thuoctinhhhcls_thuoctinhhh_thuoctinhhhgetbyidloaihang", "label": ".thuoctinhhhGetbyIdloaihang()", "file_type": "code", "source_file": "D:\\PHP_WS\\lequocanh\\administrator\\elements_LQA\\mod\\thuoctinhhhCls.php", "source_location": "L114"}, {"id": "mod_thuoctinhhhcls_thuoctinhhh_thuoctinhhhgetbyidhanghoa", "label": ".thuoctinhhhGetbyIdHanghoa()", "file_type": "code", "source_file": "D:\\PHP_WS\\lequocanh\\administrator\\elements_LQA\\mod\\thuoctinhhhCls.php", "source_location": "L130"}], "edges": [{"source": "d_php_ws_lequocanh_administrator_elements_lqa_mod_thuoctinhhhcls_php", "target": "mod_thuoctinhhhcls_thuoctinhhh", "relation": "contains", "confidence": "EXTRACTED", "source_file": "D:\\PHP_WS\\lequocanh\\administrator\\elements_LQA\\mod\\thuoctinhhhCls.php", "source_location": "L4", "weight": 1.0}, {"source": "mod_thuoctinhhhcls_thuoctinhhh", "target": "mod_thuoctinhhhcls_thuoctinhhh_construct", "relation": "method", "confidence": "EXTRACTED", "source_file": "D:\\PHP_WS\\lequocanh\\administrator\\elements_LQA\\mod\\thuoctinhhhCls.php", "source_location": "L8", "weight": 1.0}, {"source": "mod_thuoctinhhhcls_thuoctinhhh", "target": "mod_thuoctinhhhcls_thuoctinhhh_thuoctinhhhgetall", "relation": "method", "confidence": "EXTRACTED", "source_file": "D:\\PHP_WS\\lequocanh\\administrator\\elements_LQA\\mod\\thuoctinhhhCls.php", "source_location": "L13", "weight": 1.0}, {"source": "mod_thuoctinhhhcls_thuoctinhhh", "target": "mod_thuoctinhhhcls_thuoctinhhh_thuoctinhhhadd", "relation": "method", "confidence": "EXTRACTED", "source_file": "D:\\PHP_WS\\lequocanh\\administrator\\elements_LQA\\mod\\thuoctinhhhCls.php", "source_location": "L27", "weight": 1.0}, {"source": "mod_thuoctinhhhcls_thuoctinhhh", "target": "mod_thuoctinhhhcls_thuoctinhhh_thuoctinhhhdelete", "relation": "method", "confidence": "EXTRACTED", "source_file": "D:\\PHP_WS\\lequocanh\\administrator\\elements_LQA\\mod\\thuoctinhhhCls.php", "source_location": "L42", "weight": 1.0}, {"source": "mod_thuoctinhhhcls_thuoctinhhh", "target": "mod_thuoctinhhhcls_thuoctinhhh_thuoctinhhhupdate", "relation": "method", "confidence": "EXTRACTED", "source_file": "D:\\PHP_WS\\lequocanh\\administrator\\elements_LQA\\mod\\thuoctinhhhCls.php", "source_location": "L57", "weight": 1.0}, {"source": "mod_thuoctinhhhcls_thuoctinhhh", "target": "mod_thuoctinhhhcls_thuoctinhhh_thuoctinhhhgetbyid", "relation": "method", "confidence": "EXTRACTED", "source_file": "D:\\PHP_WS\\lequocanh\\administrator\\elements_LQA\\mod\\thuoctinhhhCls.php", "source_location": "L98", "weight": 1.0}, {"source": "mod_thuoctinhhhcls_thuoctinhhh", "target": "mod_thuoctinhhhcls_thuoctinhhh_thuoctinhhhgetbyidloaihang", "relation": "method", "confidence": "EXTRACTED", "source_file": "D:\\PHP_WS\\lequocanh\\administrator\\elements_LQA\\mod\\thuoctinhhhCls.php", "source_location": "L114", "weight": 1.0}, {"source": "mod_thuoctinhhhcls_thuoctinhhh", "target": "mod_thuoctinhhhcls_thuoctinhhh_thuoctinhhhgetbyidhanghoa", "relation": "method", "confidence": "EXTRACTED", "source_file": "D:\\PHP_WS\\lequocanh\\administrator\\elements_LQA\\mod\\thuoctinhhhCls.php", "source_location": "L130", "weight": 1.0}], "raw_calls": [{"caller_nid": "mod_thuoctinhhhcls_thuoctinhhh_construct", "callee": "getConnection", "is_member_call": true, "source_file": "D:\\PHP_WS\\lequocanh\\administrator\\elements_LQA\\mod\\thuoctinhhhCls.php", "source_location": "L10"}, {"caller_nid": "mod_thuoctinhhhcls_thuoctinhhh_construct", "callee": "Database", "is_member_call": false, "source_file": "D:\\PHP_WS\\lequocanh\\administrator\\elements_LQA\\mod\\thuoctinhhhCls.php", "source_location": "L10"}, {"caller_nid": "mod_thuoctinhhhcls_thuoctinhhh_thuoctinhhhgetall", "callee": "prepare", "is_member_call": true, "source_file": "D:\\PHP_WS\\lequocanh\\administrator\\elements_LQA\\mod\\thuoctinhhhCls.php", "source_location": "L16"}, {"caller_nid": "mod_thuoctinhhhcls_thuoctinhhh_thuoctinhhhgetall", "callee": "setFetchMode", "is_member_call": true, "source_file": "D:\\PHP_WS\\lequocanh\\administrator\\elements_LQA\\mod\\thuoctinhhhCls.php", "source_location": "L17"}, {"caller_nid": "mod_thuoctinhhhcls_thuoctinhhh_thuoctinhhhgetall", "callee": "execute", "is_member_call": true, "source_file": "D:\\PHP_WS\\lequocanh\\administrator\\elements_LQA\\mod\\thuoctinhhhCls.php", "source_location": "L19"}, {"caller_nid": "mod_thuoctinhhhcls_thuoctinhhh_thuoctinhhhgetall", "callee": "error_log", "is_member_call": false, "source_file": "D:\\PHP_WS\\lequocanh\\administrator\\elements_LQA\\mod\\thuoctinhhhCls.php", "source_location": "L20"}, {"caller_nid": "mod_thuoctinhhhcls_thuoctinhhh_thuoctinhhhgetall", "callee": "print_r", "is_member_call": false, "source_file": "D:\\PHP_WS\\lequocanh\\administrator\\elements_LQA\\mod\\thuoctinhhhCls.php", "source_location": "L20"}, {"caller_nid": "mod_thuoctinhhhcls_thuoctinhhh_thuoctinhhhgetall", "callee": "errorInfo", "is_member_call": true, "source_file": "D:\\PHP_WS\\lequocanh\\administrator\\elements_LQA\\mod\\thuoctinhhhCls.php", "source_location": "L20"}, {"caller_nid": "mod_thuoctinhhhcls_thuoctinhhh_thuoctinhhhgetall", "callee": "fetchAll", "is_member_call": true, "source_file": "D:\\PHP_WS\\lequocanh\\administrator\\elements_LQA\\mod\\thuoctinhhhCls.php", "source_location": "L24"}, {"caller_nid": "mod_thuoctinhhhcls_thuoctinhhh_thuoctinhhhadd", "callee": "prepare", "is_member_call": true, "source_file": "D:\\PHP_WS\\lequocanh\\administrator\\elements_LQA\\mod\\thuoctinhhhCls.php", "source_location": "L32"}, {"caller_nid": "mod_thuoctinhhhcls_thuoctinhhh_thuoctinhhhadd", "callee": "execute", "is_member_call": true, "source_file": "D:\\PHP_WS\\lequocanh\\administrator\\elements_LQA\\mod\\thuoctinhhhCls.php", "source_location": "L34"}, {"caller_nid": "mod_thuoctinhhhcls_thuoctinhhh_thuoctinhhhadd", "callee": "error_log", "is_member_call": false, "source_file": "D:\\PHP_WS\\lequocanh\\administrator\\elements_LQA\\mod\\thuoctinhhhCls.php", "source_location": "L35"}, {"caller_nid": "mod_thuoctinhhhcls_thuoctinhhh_thuoctinhhhadd", "callee": "print_r", "is_member_call": false, "source_file": "D:\\PHP_WS\\lequocanh\\administrator\\elements_LQA\\mod\\thuoctinhhhCls.php", "source_location": "L35"}, {"caller_nid": "mod_thuoctinhhhcls_thuoctinhhh_thuoctinhhhadd", "callee": "errorInfo", "is_member_call": true, "source_file": "D:\\PHP_WS\\lequocanh\\administrator\\elements_LQA\\mod\\thuoctinhhhCls.php", "source_location": "L35"}, {"caller_nid": "mod_thuoctinhhhcls_thuoctinhhh_thuoctinhhhadd", "callee": "rowCount", "is_member_call": true, "source_file": "D:\\PHP_WS\\lequocanh\\administrator\\elements_LQA\\mod\\thuoctinhhhCls.php", "source_location": "L39"}, {"caller_nid": "mod_thuoctinhhhcls_thuoctinhhh_thuoctinhhhdelete", "callee": "prepare", "is_member_call": true, "source_file": "D:\\PHP_WS\\lequocanh\\administrator\\elements_LQA\\mod\\thuoctinhhhCls.php", "source_location": "L47"}, {"caller_nid": "mod_thuoctinhhhcls_thuoctinhhh_thuoctinhhhdelete", "callee": "execute", "is_member_call": true, "source_file": "D:\\PHP_WS\\lequocanh\\administrator\\elements_LQA\\mod\\thuoctinhhhCls.php", "source_location": "L49"}, {"caller_nid": "mod_thuoctinhhhcls_thuoctinhhh_thuoctinhhhdelete", "callee": "error_log", "is_member_call": false, "source_file": "D:\\PHP_WS\\lequocanh\\administrator\\elements_LQA\\mod\\thuoctinhhhCls.php", "source_location": "L50"}, {"caller_nid": "mod_thuoctinhhhcls_thuoctinhhh_thuoctinhhhdelete", "callee": "print_r", "is_member_call": false, "source_file": "D:\\PHP_WS\\lequocanh\\administrator\\elements_LQA\\mod\\thuoctinhhhCls.php", "source_location": "L50"}, {"caller_nid": "mod_thuoctinhhhcls_thuoctinhhh_thuoctinhhhdelete", "callee": "errorInfo", "is_member_call": true, "source_file": "D:\\PHP_WS\\lequocanh\\administrator\\elements_LQA\\mod\\thuoctinhhhCls.php", "source_location": "L50"}, {"caller_nid": "mod_thuoctinhhhcls_thuoctinhhh_thuoctinhhhdelete", "callee": "rowCount", "is_member_call": true, "source_file": "D:\\PHP_WS\\lequocanh\\administrator\\elements_LQA\\mod\\thuoctinhhhCls.php", "source_location": "L54"}, {"caller_nid": "mod_thuoctinhhhcls_thuoctinhhh_thuoctinhhhupdate", "callee": "date", "is_member_call": false, "source_file": "D:\\PHP_WS\\lequocanh\\administrator\\elements_LQA\\mod\\thuoctinhhhCls.php", "source_location": "L61"}, {"caller_nid": "mod_thuoctinhhhcls_thuoctinhhh_thuoctinhhhupdate", "callee": "gettype", "is_member_call": false, "source_file": "D:\\PHP_WS\\lequocanh\\administrator\\elements_LQA\\mod\\thuoctinhhhCls.php", "source_location": "L62"}, {"caller_nid": "mod_thuoctinhhhcls_thuoctinhhh_thuoctinhhhupdate", "callee": "gettype", "is_member_call": false, "source_file": "D:\\PHP_WS\\lequocanh\\administrator\\elements_LQA\\mod\\thuoctinhhhCls.php", "source_location": "L63"}, {"caller_nid": "mod_thuoctinhhhcls_thuoctinhhh_thuoctinhhhupdate", "callee": "gettype", "is_member_call": false, "source_file": "D:\\PHP_WS\\lequocanh\\administrator\\elements_LQA\\mod\\thuoctinhhhCls.php", "source_location": "L64"}, {"caller_nid": "mod_thuoctinhhhcls_thuoctinhhh_thuoctinhhhupdate", "callee": "gettype", "is_member_call": false, "source_file": "D:\\PHP_WS\\lequocanh\\administrator\\elements_LQA\\mod\\thuoctinhhhCls.php", "source_location": "L65"}, {"caller_nid": "mod_thuoctinhhhcls_thuoctinhhh_thuoctinhhhupdate", "callee": "file_put_contents", "is_member_call": false, "source_file": "D:\\PHP_WS\\lequocanh\\administrator\\elements_LQA\\mod\\thuoctinhhhCls.php", "source_location": "L66"}, {"caller_nid": "mod_thuoctinhhhcls_thuoctinhhh_thuoctinhhhupdate", "callee": "date", "is_member_call": false, "source_file": "D:\\PHP_WS\\lequocanh\\administrator\\elements_LQA\\mod\\thuoctinhhhCls.php", "source_location": "L73"}, {"caller_nid": "mod_thuoctinhhhcls_thuoctinhhh_thuoctinhhhupdate", "callee": "print_r", "is_member_call": false, "source_file": "D:\\PHP_WS\\lequocanh\\administrator\\elements_LQA\\mod\\thuoctinhhhCls.php", "source_location": "L74"}, {"caller_nid": "mod_thuoctinhhhcls_thuoctinhhh_thuoctinhhhupdate", "callee": "file_put_contents", "is_member_call": false, "source_file": "D:\\PHP_WS\\lequocanh\\administrator\\elements_LQA\\mod\\thuoctinhhhCls.php", "source_location": "L75"}, {"caller_nid": "mod_thuoctinhhhcls_thuoctinhhh_thuoctinhhhupdate", "callee": "prepare", "is_member_call": true, "source_file": "D:\\PHP_WS\\lequocanh\\administrator\\elements_LQA\\mod\\thuoctinhhhCls.php", "source_location": "L77"}, {"caller_nid": "mod_thuoctinhhhcls_thuoctinhhh_thuoctinhhhupdate", "callee": "execute", "is_member_call": true, "source_file": "D:\\PHP_WS\\lequocanh\\administrator\\elements_LQA\\mod\\thuoctinhhhCls.php", "source_location": "L79"}, {"caller_nid": "mod_thuoctinhhhcls_thuoctinhhh_thuoctinhhhupdate", "callee": "errorInfo", "is_member_call": true, "source_file": "D:\\PHP_WS\\lequocanh\\administrator\\elements_LQA\\mod\\thuoctinhhhCls.php", "source_location": "L82"}, {"caller_nid": "mod_thuoctinhhhcls_thuoctinhhh_thuoctinhhhupdate", "callee": "date", "is_member_call": false, "source_file": "D:\\PHP_WS\\lequocanh\\administrator\\elements_LQA\\mod\\thuoctinhhhCls.php", "source_location": "L83"}, {"caller_nid": "mod_thuoctinhhhcls_thuoctinhhh_thuoctinhhhupdate", "callee": "file_put_contents", "is_member_call": false, "source_file": "D:\\PHP_WS\\lequocanh\\administrator\\elements_LQA\\mod\\thuoctinhhhCls.php", "source_location": "L87"}, {"caller_nid": "mod_thuoctinhhhcls_thuoctinhhh_thuoctinhhhupdate", "callee": "error_log", "is_member_call": false, "source_file": "D:\\PHP_WS\\lequocanh\\administrator\\elements_LQA\\mod\\thuoctinhhhCls.php", "source_location": "L88"}, {"caller_nid": "mod_thuoctinhhhcls_thuoctinhhh_thuoctinhhhupdate", "callee": "print_r", "is_member_call": false, "source_file": "D:\\PHP_WS\\lequocanh\\administrator\\elements_LQA\\mod\\thuoctinhhhCls.php", "source_location": "L88"}, {"caller_nid": "mod_thuoctinhhhcls_thuoctinhhh_thuoctinhhhupdate", "callee": "date", "is_member_call": false, "source_file": "D:\\PHP_WS\\lequocanh\\administrator\\elements_LQA\\mod\\thuoctinhhhCls.php", "source_location": "L92"}, {"caller_nid": "mod_thuoctinhhhcls_thuoctinhhh_thuoctinhhhupdate", "callee": "rowCount", "is_member_call": true, "source_file": "D:\\PHP_WS\\lequocanh\\administrator\\elements_LQA\\mod\\thuoctinhhhCls.php", "source_location": "L92"}, {"caller_nid": "mod_thuoctinhhhcls_thuoctinhhh_thuoctinhhhupdate", "callee": "file_put_contents", "is_member_call": false, "source_file": "D:\\PHP_WS\\lequocanh\\administrator\\elements_LQA\\mod\\thuoctinhhhCls.php", "source_location": "L93"}, {"caller_nid": "mod_thuoctinhhhcls_thuoctinhhh_thuoctinhhhupdate", "callee": "rowCount", "is_member_call": true, "source_file": "D:\\PHP_WS\\lequocanh\\administrator\\elements_LQA\\mod\\thuoctinhhhCls.php", "source_location": "L95"}, {"caller_nid": "mod_thuoctinhhhcls_thuoctinhhh_thuoctinhhhgetbyid", "callee": "prepare", "is_member_call": true, "source_file": "D:\\PHP_WS\\lequocanh\\administrator\\elements_LQA\\mod\\thuoctinhhhCls.php", "source_location": "L103"}, {"caller_nid": "mod_thuoctinhhhcls_thuoctinhhh_thuoctinhhhgetbyid", "callee": "setFetchMode", "is_member_call": true, "source_file": "D:\\PHP_WS\\lequocanh\\administrator\\elements_LQA\\mod\\thuoctinhhhCls.php", "source_location": "L104"}, {"caller_nid": "mod_thuoctinhhhcls_thuoctinhhh_thuoctinhhhgetbyid", "callee": "execute", "is_member_call": true, "source_file": "D:\\PHP_WS\\lequocanh\\administrator\\elements_LQA\\mod\\thuoctinhhhCls.php", "source_location": "L106"}, {"caller_nid": "mod_thuoctinhhhcls_thuoctinhhh_thuoctinhhhgetbyid", "callee": "error_log", "is_member_call": false, "source_file": "D:\\PHP_WS\\lequocanh\\administrator\\elements_LQA\\mod\\thuoctinhhhCls.php", "source_location": "L107"}, {"caller_nid": "mod_thuoctinhhhcls_thuoctinhhh_thuoctinhhhgetbyid", "callee": "print_r", "is_member_call": false, "source_file": "D:\\PHP_WS\\lequocanh\\administrator\\elements_LQA\\mod\\thuoctinhhhCls.php", "source_location": "L107"}, {"caller_nid": "mod_thuoctinhhhcls_thuoctinhhh_thuoctinhhhgetbyid", "callee": "errorInfo", "is_member_call": true, "source_file": "D:\\PHP_WS\\lequocanh\\administrator\\elements_LQA\\mod\\thuoctinhhhCls.php", "source_location": "L107"}, {"caller_nid": "mod_thuoctinhhhcls_thuoctinhhh_thuoctinhhhgetbyid", "callee": "fetch", "is_member_call": true, "source_file": "D:\\PHP_WS\\lequocanh\\administrator\\elements_LQA\\mod\\thuoctinhhhCls.php", "source_location": "L111"}, {"caller_nid": "mod_thuoctinhhhcls_thuoctinhhh_thuoctinhhhgetbyidloaihang", "callee": "prepare", "is_member_call": true, "source_file": "D:\\PHP_WS\\lequocanh\\administrator\\elements_LQA\\mod\\thuoctinhhhCls.php", "source_location": "L119"}, {"caller_nid": "mod_thuoctinhhhcls_thuoctinhhh_thuoctinhhhgetbyidloaihang", "callee": "setFetchMode", "is_member_call": true, "source_file": "D:\\PHP_WS\\lequocanh\\administrator\\elements_LQA\\mod\\thuoctinhhhCls.php", "source_location": "L120"}, {"caller_nid": "mod_thuoctinhhhcls_thuoctinhhh_thuoctinhhhgetbyidloaihang", "callee": "execute", "is_member_call": true, "source_file": "D:\\PHP_WS\\lequocanh\\administrator\\elements_LQA\\mod\\thuoctinhhhCls.php", "source_location": "L122"}, {"caller_nid": "mod_thuoctinhhhcls_thuoctinhhh_thuoctinhhhgetbyidloaihang", "callee": "error_log", "is_member_call": false, "source_file": "D:\\PHP_WS\\lequocanh\\administrator\\elements_LQA\\mod\\thuoctinhhhCls.php", "source_location": "L123"}, {"caller_nid": "mod_thuoctinhhhcls_thuoctinhhh_thuoctinhhhgetbyidloaihang", "callee": "print_r", "is_member_call": false, "source_file": "D:\\PHP_WS\\lequocanh\\administrator\\elements_LQA\\mod\\thuoctinhhhCls.php", "source_location": "L123"}, {"caller_nid": "mod_thuoctinhhhcls_thuoctinhhh_thuoctinhhhgetbyidloaihang", "callee": "errorInfo", "is_member_call": true, "source_file": "D:\\PHP_WS\\lequocanh\\administrator\\elements_LQA\\mod\\thuoctinhhhCls.php", "source_location": "L123"}, {"caller_nid": "mod_thuoctinhhhcls_thuoctinhhh_thuoctinhhhgetbyidloaihang", "callee": "fetchAll", "is_member_call": true, "source_file": "D:\\PHP_WS\\lequocanh\\administrator\\elements_LQA\\mod\\thuoctinhhhCls.php", "source_location": "L127"}, {"caller_nid": "mod_thuoctinhhhcls_thuoctinhhh_thuoctinhhhgetbyidhanghoa", "callee": "prepare", "is_member_call": true, "source_file": "D:\\PHP_WS\\lequocanh\\administrator\\elements_LQA\\mod\\thuoctinhhhCls.php", "source_location": "L135"}, {"caller_nid": "mod_thuoctinhhhcls_thuoctinhhh_thuoctinhhhgetbyidhanghoa", "callee": "setFetchMode", "is_member_call": true, "source_file": "D:\\PHP_WS\\lequocanh\\administrator\\elements_LQA\\mod\\thuoctinhhhCls.php", "source_location": "L136"}, {"caller_nid": "mod_thuoctinhhhcls_thuoctinhhh_thuoctinhhhgetbyidhanghoa", "callee": "execute", "is_member_call": true, "source_file": "D:\\PHP_WS\\lequocanh\\administrator\\elements_LQA\\mod\\thuoctinhhhCls.php", "source_location": "L138"}, {"caller_nid": "mod_thuoctinhhhcls_thuoctinhhh_thuoctinhhhgetbyidhanghoa", "callee": "error_log", "is_member_call": false, "source_file": "D:\\PHP_WS\\lequocanh\\administrator\\elements_LQA\\mod\\thuoctinhhhCls.php", "source_location": "L139"}, {"caller_nid": "mod_thuoctinhhhcls_thuoctinhhh_thuoctinhhhgetbyidhanghoa", "callee": "print_r", "is_member_call": false, "source_file": "D:\\PHP_WS\\lequocanh\\administrator\\elements_LQA\\mod\\thuoctinhhhCls.php", "source_location": "L139"}, {"caller_nid": "mod_thuoctinhhhcls_thuoctinhhh_thuoctinhhhgetbyidhanghoa", "callee": "errorInfo", "is_member_call": true, "source_file": "D:\\PHP_WS\\lequocanh\\administrator\\elements_LQA\\mod\\thuoctinhhhCls.php", "source_location": "L139"}, {"caller_nid": "mod_thuoctinhhhcls_thuoctinhhh_thuoctinhhhgetbyidhanghoa", "callee": "fetchAll", "is_member_call": true, "source_file": "D:\\PHP_WS\\lequocanh\\administrator\\elements_LQA\\mod\\thuoctinhhhCls.php", "source_location": "L143"}]}